exceltogdx/__init__.py
exceltogdx/exceltogdx.py
exceltogdx-0.0.6.dist-info/LICENSE
exceltogdx-0.0.6.dist-info/METADATA
exceltogdx-0.0.6.dist-info/WHEEL
exceltogdx-0.0.6.dist-info/top_level.txt
exceltogdx-0.0.6.dist-info/RECORD
