Metadata-Version: 2.1
Name: exceltogdx
Version: 0.0.6
Summary: A simple python tool to extract sets and parameters from excel files by creating GDX files for GAMS
Home-page: UNKNOWN
Author: Carlos Gaete
Author-email: cdgaete@gmail.com
License: MIT License        
Platform: UNKNOWN
Classifier: Intended Audience :: End Users/Desktop
Classifier: Intended Audience :: Developers
Classifier: Intended Audience :: Science/Research
Classifier: License :: OSI Approved :: MIT License
Classifier: Operating System :: MacOS :: MacOS X
Classifier: Operating System :: Microsoft :: Windows
Classifier: Operating System :: POSIX
Classifier: Programming Language :: Python
Classifier: Programming Language :: Python :: 3
Classifier: Programming Language :: Python :: 3.6
Classifier: Programming Language :: Python :: 3.7
Classifier: Programming Language :: Python :: 3.8
Classifier: Programming Language :: Python :: 3.9
Classifier: Topic :: Scientific/Engineering :: Information Analysis
Classifier: Topic :: Scientific/Engineering :: Mathematics
License-File: LICENSE
Requires-Dist: pandas
Requires-Dist: numpy
Requires-Dist: openpyxl
Requires-Dist: gdxpds
